pyscaffoldext/nox/__init__.py
pyscaffoldext/nox/extension.py
pyscaffoldext/nox/templates/__init__.py
pyscaffoldext/nox/templates/noxfile.py.template
pyscaffoldext_nox-0.0.9.dist-info/LICENSE.txt
pyscaffoldext_nox-0.0.9.dist-info/METADATA
pyscaffoldext_nox-0.0.9.dist-info/WHEEL
pyscaffoldext_nox-0.0.9.dist-info/entry_points.txt
pyscaffoldext_nox-0.0.9.dist-info/top_level.txt
pyscaffoldext_nox-0.0.9.dist-info/RECORD
