Metadata-Version: 2.1
Name: pyscaffoldext-nox
Version: 0.0.9
Summary: Use nox in scaffolding
Home-page: https://github.com/jaustinpage/pyscaffoldext-nox/
Author: Austin Page
Author-email: jaustinpage@gmail.com
License: MIT
Project-URL: Documentation, https://pyscaffold.org/
Platform: any
Classifier: Development Status :: 4 - Beta
Classifier: Programming Language :: Python
License-File: LICENSE.txt
Requires-Dist: pyscaffold (<5.0a0,>=4.2)
Requires-Dist: importlib-metadata ; python_version < "3.8"
Provides-Extra: testing
Requires-Dist: nox ; extra == 'testing'
Requires-Dist: pre-commit ; extra == 'testing'
Requires-Dist: setuptools-scm ; extra == 'testing'
Requires-Dist: virtualenv ; extra == 'testing'
Requires-Dist: configupdater ; extra == 'testing'
Requires-Dist: pytest ; extra == 'testing'
Requires-Dist: pytest-cov ; extra == 'testing'
Requires-Dist: pytest-xdist ; extra == 'testing'
